ontology/__init__.py
ontology/ont_sdk.py
ontology/account/__init__.py
ontology/account/account.py
ontology/claim/__init__.py
ontology/claim/claim.py
ontology/claim/header.py
ontology/claim/payload.py
ontology/claim/proof.py
ontology/common/__init__.py
ontology/common/address.py
ontology/common/define.py
ontology/common/wallet_qr.py
ontology/core/__init__.py
ontology/core/deploy_transaction.py
ontology/core/invoke_transaction.py
ontology/core/program.py
ontology/core/program_info.py
ontology/core/sig.py
ontology/core/transaction.py
ontology/crypto/__init__.py
ontology/crypto/aes_handler.py
ontology/crypto/curve.py
ontology/crypto/digest.py
ontology/crypto/ecies.py
ontology/crypto/kdf.py
ontology/crypto/key_type.py
ontology/crypto/mnemonic_code.py
ontology/crypto/scrypt.py
ontology/crypto/signature.py
ontology/crypto/signature_handler.py
ontology/crypto/signature_scheme.py
ontology/exception/__init__.py
ontology/exception/error_code.py
ontology/exception/exception.py
ontology/io/__init__.py
ontology/io/binary_reader.py
ontology/io/binary_writer.py
ontology/io/memory_stream.py
ontology/merkle/__init__.py
ontology/merkle/merkle_verifier.py
ontology/merkle/tx_verifier.py
ontology/network/__init__.py
ontology/network/restful.py
ontology/network/rpc.py
ontology/network/websocket.py
ontology/service/__init__.py
ontology/service/service.py
ontology/sigsvr/__init__.py
ontology/sigsvr/sigsvr.py
ontology/smart_contract/__init__.py
ontology/smart_contract/native_vm.py
ontology/smart_contract/neo_vm.py
ontology/smart_contract/native_contract/__init__.py
ontology/smart_contract/native_contract/asset.py
ontology/smart_contract/native_contract/governance.py
ontology/smart_contract/native_contract/ontid.py
ontology/smart_contract/neo_contract/__init__.py
ontology/smart_contract/neo_contract/claim_record.py
ontology/smart_contract/neo_contract/invoke_function.py
ontology/smart_contract/neo_contract/oep4.py
ontology/smart_contract/neo_contract/oep8.py
pandora_python_sdk-0.0.1.dist-info/LICENSE
pandora_python_sdk-0.0.1.dist-info/METADATA
pandora_python_sdk-0.0.1.dist-info/WHEEL
pandora_python_sdk-0.0.1.dist-info/top_level.txt
pandora_python_sdk-0.0.1.dist-info/RECORD
